plixkws/backbone.py
plixkws/model.py
plixkws/protonet.py
plixkws/util.py
plixkws-1.0.dist-info/LICENSE
plixkws-1.0.dist-info/METADATA
plixkws-1.0.dist-info/WHEEL
plixkws-1.0.dist-info/top_level.txt
plixkws-1.0.dist-info/RECORD
