Metadata-Version: 2.1
Name: plixkws
Version: 1.0
Summary: Plug-and-Play Multilingual Few-shot Spoken Words Recognition
Home-page: https://github.com/FewshotML/plix
Download-URL: https://pypi.org/project/plixkws/
Author: Aaqib Saeed
Author-email: aqibsaeed@protonmail.com
License: Apache-2.0
Keywords: Keyword Spotting,Few-shot Learning,Deep Neural Network,Audio,Speech
License-File: LICENSE
Requires-Dist: torch
Requires-Dist: torchvision
Requires-Dist: torchaudio
Requires-Dist: timm
Requires-Dist: wget
Requires-Dist: librosa
